topoindex/__init__.py
topoindex/cli.py
topoindex/core.py
topoindex/indices/__init__.py
topoindex/indices/balaban.py
topoindex/indices/eccentric_connectivity.py
topoindex/indices/hyper_wiener.py
topoindex/indices/randic.py
topoindex/indices/wiener.py
topoindex/indices/zagreb.py
topoindex/utils/__init__.py
topoindex/utils/graph_utils.py
topoindex/utils/smiles_to_nx.py
topoindex-0.1.6.dist-info/licenses/LICENSE
topoindex-0.1.6.dist-info/METADATA
topoindex-0.1.6.dist-info/WHEEL
topoindex-0.1.6.dist-info/entry_points.txt
topoindex-0.1.6.dist-info/top_level.txt
topoindex-0.1.6.dist-info/RECORD
