Metadata-Version: 2.4
Name: topoindex
Version: 0.1.6
Summary: A Python library for computing topological indices from SMILES using NetworkX
Home-page: https://github.com/avimallick/topoindex
Author: Avinash Mallick
Author-email: avimallick@gmail.com
License: MIT
Classifier: Programming Language :: Python :: 3
Classifier: License :: OSI Approved :: MIT License
Classifier: Operating System :: OS Independent
Requires-Python: >=3.8
License-File: LICENSE
Requires-Dist: networkx
Requires-Dist: rdkit
Requires-Dist: pandas
Dynamic: author
Dynamic: author-email
Dynamic: classifier
Dynamic: description
Dynamic: description-content-type
Dynamic: home-page
Dynamic: license
Dynamic: license-file
Dynamic: requires-dist
Dynamic: requires-python
Dynamic: summary
